[{"en":"feasibility","af":"uitvoerbaarheid"},{"en":"feasibility analysis","af":"uitvoerbaarheidsontleding"},{"en":"feasibility assessment","af":"uitvoerbaarheidsbepaling"},{"en":"feasibility study","af":"uitvoerbaarheidstudie"},{"en":"feasible","af":"uitvoerbaar"},{"en":"feasible solution","af":"uitvoerbare oplossing"},{"en":"feature","af":"kenmerk"},{"en":"feed","af":"voer"},{"en":"feed back","af":"terugkoppel; terugvoer"},{"en":"feed hole","af":"tandvoergat"},{"en":"feed rate","af":"voertempo"},{"en":"feed reel","af":"voerspoel"},{"en":"feed track","af":"voerbaan"},{"en":"feedback","af":"terugkoppeling; terugvoering"},{"en":"feedback amplifier","af":"terugkoppelversterker"},{"en":"feedback control","af":"terugkoppelingsbeheer"},{"en":"feedback impedance","af":"terugkoppelimpedansie"},{"en":"feedback loop","af":"terugkoppellus; terugvoerlus"},{"en":"feedback signal","af":"terugkoppelsein"},{"en":"feeder","af":"voerder"},{"en":"feeder cable","af":"voerderkabel"},{"en":"feeding","af":"voer"},{"en":"female connector","af":"sok"},{"en":"female plug","af":"sok"},{"en":"femtosecond","af":"femtosekonde"},{"en":"ferric oxide","af":"ferri-oksied"},{"en":"ferrite core","af":"ferrietkern"},{"en":"ferromagnetic","af":"ferromagneties"},{"en":"FET","af":"VET; veldeffektransistor"},{"en":"fetch","af":"haal"},{"en":"fetch cycle","af":"haalsiklus"},{"en":"fetch instruction","af":"haalinstruksie"},{"en":"fetch process","af":"haalproses"},{"en":"fetch protection","af":"haalbeskerming"},{"en":"fetch routine","af":"haalroetine"},{"en":"fetch/execute cycle","af":"haal/uitvoer-siklus"}]